{
 "id":"1631814157",
 "name":"birds and snakes and aeroplanes",
 "screen_name":"nota_bennett",
 "tweets":[
  {"id":"1206311808572653569","timestamp":"1576442122","retweet_count":"7","favorite_count":"46","in_reply_to_status_id":"null","in_reply_to_user_id":"null","in_reply_to_screen_name":"null","text":"On suggestion from @vgr I’m going to do a few of these\n\n1 like = 1 opinion about... learning\n\nStarting with:\n\nIf you want to get depressed get to know a class of Education students (some individuals will be great but most will destroy a little piece of your soul)"},
  {"id":"1206311809654722560","timestamp":"1576442122","retweet_count":"1","favorite_count":"22","in_reply_to_status_id":"1206311808572653569","in_reply_to_user_id":"1631814157","in_reply_to_screen_name":"nota_bennett","text":"1 like = 1 opinion about... software engineers\n\nStarting with:\n\nThe industry and practice has largely been warped around what software engineers think they want, at the expense of what’s effective &amp; actually makes them happy"},
  {"id":"1206311810548133888","timestamp":"1576442122","retweet_count":"0","favorite_count":"15","in_reply_to_status_id":"1206311809654722560","in_reply_to_user_id":"1631814157","in_reply_to_screen_name":"nota_bennett","text":"1 like = 1 opinion about... leadership\n\nStarting with:\n\nMost people with formal leadership roles aren’t competent at them."},
  {"id":"1206311811336638464","timestamp":"1576442122","retweet_count":"0","favorite_count":"9","in_reply_to_status_id":"1206311810548133888","in_reply_to_user_id":"1631814157","in_reply_to_screen_name":"nota_bennett","text":"1 like = 1 opinion about Los Angeles (which I am woefully under qualified to comment on but I have feelings, people)\n\nLet’s start this one with\nEvery Los Angeles burrito I have ever had has been better than every San Francisco burrito I have ever had"},
  {"id":"1206321575835815938","timestamp":"1576444450","retweet_count":"0","favorite_count":"1","in_reply_to_status_id":"1206311811336638464","in_reply_to_user_id":"1631814157","in_reply_to_screen_name":"nota_bennett","text":"1. Los Angeles is *weird*\n\nLike weird the way that San Francisco was supposed to be weird"},
  {"id":"1206324783316488192","timestamp":"1576445215","retweet_count":"0","favorite_count":"0","in_reply_to_status_id":"1206321575835815938","in_reply_to_user_id":"1631814157","in_reply_to_screen_name":"nota_bennett","text":"2. Not having seasons is objectively good and I don’t understand why anyone complains about this"},
  {"id":"1206340902198767617","timestamp":"1576449058","retweet_count":"0","favorite_count":"0","in_reply_to_status_id":"1206324783316488192","in_reply_to_user_id":"1631814157","in_reply_to_screen_name":"nota_bennett","text":"3. I was not prepared for how many European youths there are in (my particular corner of) Venice, especially Eastern European and French teens."},
  {"id":"1206435552553123841","timestamp":"1576471624","retweet_count":"0","favorite_count":"1","in_reply_to_status_id":"1206340902198767617","in_reply_to_user_id":"1631814157","in_reply_to_screen_name":"nota_bennett","text":"4. Los Angeles is extremely America, probably the most American city I've lived in."},
  {"id":"1206315616887431168","timestamp":"1576443029","retweet_count":"0","favorite_count":"2","in_reply_to_status_id":"1206311810548133888","in_reply_to_user_id":"1631814157","in_reply_to_screen_name":"nota_bennett","text":"1. Leadership is mostly seeing clearly— especially what the meta-seeing of what your teammates are and aren’t seeing."},
  {"id":"1206315617822789632","timestamp":"1576443030","retweet_count":"0","favorite_count":"3","in_reply_to_status_id":"1206315616887431168","in_reply_to_user_id":"1631814157","in_reply_to_screen_name":"nota_bennett","text":"2. The most important skills for leadership are the skills that cause a group to identify you as a leader and these mostly aren’t skills, they’re accidents of group dynamics and social status, oops"},
  {"id":"1206321254388527104","timestamp":"1576444374","retweet_count":"0","favorite_count":"2","in_reply_to_status_id":"1206315617822789632","in_reply_to_user_id":"1631814157","in_reply_to_screen_name":"nota_bennett","text":"3. You could do a lot worse for a leader than someone tall, good looking, good at listening, and aware that their job is mostly to tell people they already know what todo &amp; occasionally break ties"},
  {"id":"1206321255395102721","timestamp":"1576444374","retweet_count":"0","favorite_count":"3","in_reply_to_status_id":"1206321254388527104","in_reply_to_user_id":"1631814157","in_reply_to_screen_name":"nota_bennett","text":"4. The military is the only organization that seriously studies leadership and even they aren’t particularly good at it\n\n(Lots of people unseriously study leadership but we aren’t going to talk about MBAs here)"},
  {"id":"1206325393659027457","timestamp":"1576445360","retweet_count":"0","favorite_count":"3","in_reply_to_status_id":"1206321255395102721","in_reply_to_user_id":"1631814157","in_reply_to_screen_name":"nota_bennett","text":"5. Hierarchy is required for large organizations to have inclusive decision-making, because it’s necessary to make decision-making legible."},
  {"id":"1206435035781271552","timestamp":"1576471501","retweet_count":"0","favorite_count":"1","in_reply_to_status_id":"1206325393659027457","in_reply_to_user_id":"1631814157","in_reply_to_screen_name":"nota_bennett","text":"6. The dominant factor for leaders, especially formal ones -- and like Hofstadter's law, this is under-appreciated even by folks who know about it -- is that you know maybe 5% of what's happening at the layer below you, and even less of the layer below that."},
  {"id":"1206435037169602562","timestamp":"1576471501","retweet_count":"0","favorite_count":"1","in_reply_to_status_id":"1206435035781271552","in_reply_to_user_id":"1631814157","in_reply_to_screen_name":"nota_bennett","text":"7. Your boss very literally does not know what is going on. They can't. There is so much more happening than they can possibly know, even before incentives to hide information come into play. It is a goddamned miracle when a VP has any sense at all of what line ICs are up to."},
  {"id":"1206435040336338944","timestamp":"1576471502","retweet_count":"0","favorite_count":"1","in_reply_to_status_id":"1206435037169602562","in_reply_to_user_id":"1631814157","in_reply_to_screen_name":"nota_bennett","text":"8. The Wire is the very best media illustration of this principle that I have ever seen. It is majestic."},
  {"id":"1206435041410072576","timestamp":"1576471503","retweet_count":"0","favorite_count":"1","in_reply_to_status_id":"1206435040336338944","in_reply_to_user_id":"1631814157","in_reply_to_screen_name":"nota_bennett","text":"9. Sometimes people will argue about command-and-control vs. empowerment leadership.\n\nGuess what! Command-and-control does not and cannot work! There's no world where Just Telling People What To Do will produce the results you intend. You just get headless orgs instead."},
  {"id":"1206435042534154240","timestamp":"1576471503","retweet_count":"0","favorite_count":"1","in_reply_to_status_id":"1206435041410072576","in_reply_to_user_id":"1631814157","in_reply_to_screen_name":"nota_bennett","text":"10. Most organizations are basically headless, the layers on the ground only having the vaguest of alignment with each other and with their supposed \"leaders.\""},
  {"id":"1206315137604284416","timestamp":"1576442915","retweet_count":"2","favorite_count":"8","in_reply_to_status_id":"1206311809654722560","in_reply_to_user_id":"1631814157","in_reply_to_screen_name":"nota_bennett","text":"1. (‘cause we’re zero indexed here)\n\nA lot of dysfunction in software engineering comes from my generation of software engineers was pretty badly lied to in school— we got sold Computers as a good career to avoid talking to people.\n\nWhat a funny joke for everyone to enjoy."},
  {"id":"1206315138736721921","timestamp":"1576442915","retweet_count":"0","favorite_count":"4","in_reply_to_status_id":"1206315137604284416","in_reply_to_user_id":"1631814157","in_reply_to_screen_name":"nota_bennett","text":"2. Corollary to above, this is part of why many of the best engineers are 2nd career folks or otherwise non-CS — we knew what we were getting into— and actually like it!"},
  {"id":"1206315139651125248","timestamp":"1576442916","retweet_count":"0","favorite_count":"5","in_reply_to_status_id":"1206315138736721921","in_reply_to_user_id":"1631814157","in_reply_to_screen_name":"nota_bennett","text":"3. Most software engineer software have way too low of standards for how good our working conditions can be... and not nearly enough appreciation for how much skill good working conditions require."},
  {"id":"1206315140540334080","timestamp":"1576442916","retweet_count":"0","favorite_count":"6","in_reply_to_status_id":"1206315139651125248","in_reply_to_user_id":"1631814157","in_reply_to_screen_name":"nota_bennett","text":"4. Software engineers who think “pairing doesn’t work” or “I don’t like pairing” either aren’t very good at it or have only paired with people who aren’t good at it."},
  {"id":"1206319748750823424","timestamp":"1576444015","retweet_count":"0","favorite_count":"2","in_reply_to_status_id":"1206315140540334080","in_reply_to_user_id":"1631814157","in_reply_to_screen_name":"nota_bennett","text":"5. Most software engineering opinions are pointless and/or fashion. This is a feature not a bug— being able to detect other engineers who share my aesthetic and cultural preferences is more important than using the right tool."},
  {"id":"1206319749791014912","timestamp":"1576444015","retweet_count":"1","favorite_count":"5","in_reply_to_status_id":"1206319748750823424","in_reply_to_user_id":"1631814157","in_reply_to_screen_name":"nota_bennett","text":"6. Software engineering is mostly a jobs program for mediocre white men"},
  {"id":"1206319750625710080","timestamp":"1576444015","retweet_count":"0","favorite_count":"4","in_reply_to_status_id":"1206319749791014912","in_reply_to_user_id":"1631814157","in_reply_to_screen_name":"nota_bennett","text":"7. The best software engineers are mostly mediocre white men who understand that they’re mediocre and are cool with that"},
  {"id":"1206319751477088256","timestamp":"1576444015","retweet_count":"0","favorite_count":"4","in_reply_to_status_id":"1206319750625710080","in_reply_to_user_id":"1631814157","in_reply_to_screen_name":"nota_bennett","text":"8. The worst software engineers are the best programmers. Past a certain point being great at writing code is an obstacle to doing great engineering."},
  {"id":"1206324455519051777","timestamp":"1576445137","retweet_count":"3","favorite_count":"9","in_reply_to_status_id":"1206319751477088256","in_reply_to_user_id":"1631814157","in_reply_to_screen_name":"nota_bennett","text":"9. Software engineers like computers because they are basically incomprehensible but their incomprehensibility is bounded and describable\n\nCompare to humans, who are basically comprehensible but infinite &amp; indescribable"},
  {"id":"1206343550750773248","timestamp":"1576449689","retweet_count":"0","favorite_count":"1","in_reply_to_status_id":"1206324455519051777","in_reply_to_user_id":"1631814157","in_reply_to_screen_name":"nota_bennett","text":"10. Software engineer appears to be the only easily(ish) accessible job that's any good any more and that scares me."},
  {"id":"1206343551878959104","timestamp":"1576449690","retweet_count":"0","favorite_count":"1","in_reply_to_status_id":"1206343550750773248","in_reply_to_user_id":"1631814157","in_reply_to_screen_name":"nota_bennett","text":"11. The other option is that successful software engineers are super segregated from successful &lt;other things&gt; and that scares me even more.\n\nI think I have some friends-of-friends who are... lawyers? Maybe? I don't know what other jobs are even available anymore."},
  {"id":"1206343552944312320","timestamp":"1576449690","retweet_count":"0","favorite_count":"1","in_reply_to_status_id":"1206343551878959104","in_reply_to_user_id":"1631814157","in_reply_to_screen_name":"nota_bennett","text":"12. There's no good way to measure software engineer performance, it's impossible, just stop."},
  {"id":"1206343554097795074","timestamp":"1576449690","retweet_count":"0","favorite_count":"1","in_reply_to_status_id":"1206343552944312320","in_reply_to_user_id":"1631814157","in_reply_to_screen_name":"nota_bennett","text":"13. Really bad software engineers are usually (like most people who are bad at things) scared software engineers."},
  {"id":"1206433249364328448","timestamp":"1576471075","retweet_count":"0","favorite_count":"1","in_reply_to_status_id":"1206343554097795074","in_reply_to_user_id":"1631814157","in_reply_to_screen_name":"nota_bennett","text":"14. As software engineers we're a lot more like brick layers than we are like lawyers but we like to pretend otherwise."},
  {"id":"1206433250660405248","timestamp":"1576471076","retweet_count":"0","favorite_count":"0","in_reply_to_status_id":"1206433249364328448","in_reply_to_user_id":"1631814157","in_reply_to_screen_name":"nota_bennett","text":"15. Alternatively we're a new information management helper to the ruling class/scribe class."},
  {"id":"1206433251956363266","timestamp":"1576471076","retweet_count":"0","favorite_count":"1","in_reply_to_status_id":"1206433250660405248","in_reply_to_user_id":"1631814157","in_reply_to_screen_name":"nota_bennett","text":"16. A lot of the tech goofuses everyone loves to hate are not, in fact, engineers, which is a fact I'm not sure is especially clear to people outside the tech bubble."},
  {"id":"1206433253550223360","timestamp":"1576471076","retweet_count":"0","favorite_count":"1","in_reply_to_status_id":"1206433251956363266","in_reply_to_user_id":"1631814157","in_reply_to_screen_name":"nota_bennett","text":"17. Almost all the software engineers I know well enough to talk politics with (including and especially the managers) are borderline communists, which probably says more about me and my crowd than it does about software engineers."},
  {"id":"1206433255056035840","timestamp":"1576471077","retweet_count":"0","favorite_count":"0","in_reply_to_status_id":"1206433253550223360","in_reply_to_user_id":"1631814157","in_reply_to_screen_name":"nota_bennett","text":"18. The engineers I respect the most are almost all really funny. Again this probably says more about me than it does the class but there's a lot that's absurd about our work and I think it's a sign of a well-organized mind to appreciate that."},
  {"id":"1206318629869907968","timestamp":"1576443748","retweet_count":"13","favorite_count":"43","in_reply_to_status_id":"1206311808572653569","in_reply_to_user_id":"1631814157","in_reply_to_screen_name":"nota_bennett","text":"@vgr 1. Being good at learning is mostly believing that you’re good at it and, therefore, giving yourself sufficient time to fuck around"},
  {"id":"1206318631056900096","timestamp":"1576443748","retweet_count":"0","favorite_count":"11","in_reply_to_status_id":"1206318629869907968","in_reply_to_user_id":"1631814157","in_reply_to_screen_name":"nota_bennett","text":"2. Most people are kind of fucked up about learning because school by and large destroys your ability to learn while all the adults around you tell you how Important it is"},
  {"id":"1206318631967051776","timestamp":"1576443748","retweet_count":"0","favorite_count":"6","in_reply_to_status_id":"1206318631056900096","in_reply_to_user_id":"1631814157","in_reply_to_screen_name":"nota_bennett","text":"3. Learning is a largely destructive process, especially past about age 25"},
  {"id":"1206318632810074112","timestamp":"1576443749","retweet_count":"0","favorite_count":"8","in_reply_to_status_id":"1206318631967051776","in_reply_to_user_id":"1631814157","in_reply_to_screen_name":"nota_bennett","text":"4. Kids are better at learning e.g. languages mostly because they’re more motivated than adults (what the hell is everyone saying) and have more time"},
  {"id":"1206318633770598400","timestamp":"1576443749","retweet_count":"0","favorite_count":"3","in_reply_to_status_id":"1206318632810074112","in_reply_to_user_id":"1631814157","in_reply_to_screen_name":"nota_bennett","text":"5. Classroom instruction, as a career and as a service, mostly attracts and rewards psychopaths"},
  {"id":"1206318634651357184","timestamp":"1576443749","retweet_count":"0","favorite_count":"4","in_reply_to_status_id":"1206318633770598400","in_reply_to_user_id":"1631814157","in_reply_to_screen_name":"nota_bennett","text":"6. I’m extremely good at learning and extremely bad at studying and I believe that this is evidence that studying is mostly a waste of time but probably mostly what it means is that my memory is very good— both writing and reading are *fast*"},
  {"id":"1206318635704172545","timestamp":"1576443749","retweet_count":"1","favorite_count":"6","in_reply_to_status_id":"1206318634651357184","in_reply_to_user_id":"1631814157","in_reply_to_screen_name":"nota_bennett","text":"7. Most humans have an innate sense of what’s valuable for them to learn and everyone would be happier if we left kids alone to follow that more"},
  {"id":"1206320484033282048","timestamp":"1576444190","retweet_count":"0","favorite_count":"3","in_reply_to_status_id":"1206318635704172545","in_reply_to_user_id":"1631814157","in_reply_to_screen_name":"nota_bennett","text":"8. Learning lots of things a little bit is better than learning one thing a lot because it’s less useful"},
  {"id":"1206320485165715456","timestamp":"1576444190","retweet_count":"0","favorite_count":"7","in_reply_to_status_id":"1206320484033282048","in_reply_to_user_id":"1631814157","in_reply_to_screen_name":"nota_bennett","text":"9. Learning takes a lot of energy and if you’re doing it a lot you should take a lot of naps to clean your brain out"},
  {"id":"1206320486050758656","timestamp":"1576444190","retweet_count":"0","favorite_count":"3","in_reply_to_status_id":"1206320485165715456","in_reply_to_user_id":"1631814157","in_reply_to_screen_name":"nota_bennett","text":"10. Learning and genetic adaptation are the same process on different time scales"},
  {"id":"1206320486927351808","timestamp":"1576444191","retweet_count":"4","favorite_count":"5","in_reply_to_status_id":"1206320486050758656","in_reply_to_user_id":"1631814157","in_reply_to_screen_name":"nota_bennett","text":"11. Rocks can learn, mostly about which places are and aren’t good for rocks to be"},
  {"id":"1206322133770485760","timestamp":"1576444583","retweet_count":"0","favorite_count":"4","in_reply_to_status_id":"1206320486927351808","in_reply_to_user_id":"1631814157","in_reply_to_screen_name":"nota_bennett","text":"12. Most improvements in my capacity to learn have been improvements in my belief in my ability to learn.\n\nLike, learning ping pong improved my ability to learn physical skills in general because I proved to myself I could go from “awful” to “actually pretty good”"},
  {"id":"1206322381448302593","timestamp":"1576444642","retweet_count":"0","favorite_count":"12","in_reply_to_status_id":"1206322133770485760","in_reply_to_user_id":"1631814157","in_reply_to_screen_name":"nota_bennett","text":"13. Most things worth knowing are learned accidentally and unconsciously."},
  {"id":"1206323898096091136","timestamp":"1576445004","retweet_count":"0","favorite_count":"3","in_reply_to_status_id":"1206322381448302593","in_reply_to_user_id":"1631814157","in_reply_to_screen_name":"nota_bennett","text":"14. I’m underselling my own learning ability a little bit because the other thing that makes me good at it is an obsessive drive to chew every experience I have apart to extract maximum learning meats from it\n\nThis is mostly not good for me"},
  {"id":"1206323899106910209","timestamp":"1576445004","retweet_count":"0","favorite_count":"2","in_reply_to_status_id":"1206323898096091136","in_reply_to_user_id":"1631814157","in_reply_to_screen_name":"nota_bennett","text":"15. Eating and learning are also basically the same process"},
  {"id":"1206325892533739521","timestamp":"1576445479","retweet_count":"0","favorite_count":"3","in_reply_to_status_id":"1206323899106910209","in_reply_to_user_id":"1631814157","in_reply_to_screen_name":"nota_bennett","text":"16. If you can avoid learning you probably should. Do something useful with your time instead."},
  {"id":"1206342030814666758","timestamp":"1576449327","retweet_count":"0","favorite_count":"3","in_reply_to_status_id":"1206325892533739521","in_reply_to_user_id":"1631814157","in_reply_to_screen_name":"nota_bennett","text":"17. On the other hand if you're an entity you're probably constantly learning and can't help it, learning is just having experiences and being changed by them."},
  {"id":"1206342032047792129","timestamp":"1576449327","retweet_count":"1","favorite_count":"9","in_reply_to_status_id":"1206342030814666758","in_reply_to_user_id":"1631814157","in_reply_to_screen_name":"nota_bennett","text":"18. *Un*learning is a really underappreciated skill, this is mostly what therapy is about."},
  {"id":"1206342032962146304","timestamp":"1576449328","retweet_count":"0","favorite_count":"2","in_reply_to_status_id":"1206342032047792129","in_reply_to_user_id":"1631814157","in_reply_to_screen_name":"nota_bennett","text":"19. Restating a couple of earlier points into something more Useful\n\nLearning is interest + time. You can fake the former but it's better to cultivate and discover it."},
  {"id":"1206342034111356928","timestamp":"1576449328","retweet_count":"0","favorite_count":"1","in_reply_to_status_id":"1206342032962146304","in_reply_to_user_id":"1631814157","in_reply_to_screen_name":"nota_bennett","text":"20. One interesting way that animals can vary is, how long of association chains can they learn. Some cats can link 2 events but not 3."},
  {"id":"1206342443253161984","timestamp":"1576449425","retweet_count":"0","favorite_count":"5","in_reply_to_status_id":"1206342034111356928","in_reply_to_user_id":"1631814157","in_reply_to_screen_name":"nota_bennett","text":"21. It's really easy to over-learn and over-generalize. At 30 I'm mostly focused on being worse at learning -- learning more slowly and more deliberately."},
  {"id":"1206342444167528448","timestamp":"1576449426","retweet_count":"0","favorite_count":"0","in_reply_to_status_id":"1206342443253161984","in_reply_to_user_id":"1631814157","in_reply_to_screen_name":"nota_bennett","text":"22. Probably the most fun thing I've done recently, though, was to pick up a skill that's very different from what I do in every day life. (Photography.)"},
  {"id":"1206346709288120320","timestamp":"1576450442","retweet_count":"0","favorite_count":"5","in_reply_to_status_id":"1206342444167528448","in_reply_to_user_id":"1631814157","in_reply_to_screen_name":"nota_bennett","text":"23. I like the \"dive in and quit\" heuristic for learning. Most of the major skills that I'm actively \"working on\" cycle in and out of my life on a cadence of months or years."},
  {"id":"1206346710294728704","timestamp":"1576450443","retweet_count":"0","favorite_count":"3","in_reply_to_status_id":"1206346709288120320","in_reply_to_user_id":"1631814157","in_reply_to_screen_name":"nota_bennett","text":"24. The really key thing for learning quickly is feedback. If you can get instant feedback about whether you've done something well or not you're going to do much better than if you have to wait hours or days."},
  {"id":"1206431001980719104","timestamp":"1576470539","retweet_count":"1","favorite_count":"3","in_reply_to_status_id":"1206346710294728704","in_reply_to_user_id":"1631814157","in_reply_to_screen_name":"nota_bennett","text":"25. Some of the most confused, unhappiest people I know are the ones who spent a bunch of time studying things that didn't turn out to be good for them."},
  {"id":"1206431003566166016","timestamp":"1576470540","retweet_count":"0","favorite_count":"3","in_reply_to_status_id":"1206431001980719104","in_reply_to_user_id":"1631814157","in_reply_to_screen_name":"nota_bennett","text":"26. A lot of hobbies are basically learning for fun, plus some component of either showing off what you learned for social status, or entering flow-state on command."},
  {"id":"1206431013112442880","timestamp":"1576470542","retweet_count":"0","favorite_count":"4","in_reply_to_status_id":"1206431003566166016","in_reply_to_user_id":"1631814157","in_reply_to_screen_name":"nota_bennett","text":"27. One of the many, many disservices formal schooling does to humans is it teaches us that \"learning\" is this distinct activity that takes place in certain zones-- and can be optimized by experts."},
  {"id":"1206431014131625985","timestamp":"1576470542","retweet_count":"0","favorite_count":"2","in_reply_to_status_id":"1206431013112442880","in_reply_to_user_id":"1631814157","in_reply_to_screen_name":"nota_bennett","text":"28. I mean who knows maybe it *can* be optimized by experts, but my experience has been that learning is damaged by teachers more often than it is facilitated by them."},
  {"id":"1206431017646641152","timestamp":"1576470543","retweet_count":"0","favorite_count":"1","in_reply_to_status_id":"1206431014131625985","in_reply_to_user_id":"1631814157","in_reply_to_screen_name":"nota_bennett","text":"29. Teaching has a similar addictive charge to it as standup comedy and you have to be real careful about your motives if you're going to do it."},
  {"id":"1206431906448805889","timestamp":"1576470755","retweet_count":"0","favorite_count":"0","in_reply_to_status_id":"1206431017646641152","in_reply_to_user_id":"1631814157","in_reply_to_screen_name":"nota_bennett","text":"30. I was a writing tutor in college, education students cannot write for shit."},
  {"id":"1206431907895894016","timestamp":"1576470755","retweet_count":"0","favorite_count":"2","in_reply_to_status_id":"1206431906448805889","in_reply_to_user_id":"1631814157","in_reply_to_screen_name":"nota_bennett","text":"31. I think it's kind of corrosive how much of our learning-energy gets channeled towards a narrowly-defined productive effort. We're designed as animals to poke around in weird holes and realize why it was useful later."},
  {"id":"1206431909456171008","timestamp":"1576470756","retweet_count":"0","favorite_count":"1","in_reply_to_status_id":"1206431907895894016","in_reply_to_user_id":"1631814157","in_reply_to_screen_name":"nota_bennett","text":"32. It's probably our capacity to deliberately teach that sets humans apart from other animals, more than our ability to learn. (Though, we're less apart from other animals than we think, always.)"},
  {"id":"1206431910840291329","timestamp":"1576470756","retweet_count":"0","favorite_count":"0","in_reply_to_status_id":"1206431909456171008","in_reply_to_user_id":"1631814157","in_reply_to_screen_name":"nota_bennett","text":"33. As a puppy my dog tried to eat a toad-- and immediately spat it back out and sat down very hard.\n\nThe next year, he remembered that toads were scary but not that he shouldn't eat them."}
 ]
}
